{
  "id": 11564,
  "annotations": [
    {
      "id": 2435,
      "completed_by": 1,
      "result": [
        {
          "original_width": 640,
          "original_height": 480,
          "image_rotation": 0,
          "value": {
            "points": [
              [
                0,
                14.810549282983912
              ],
              [
                5.2036517591715885,
                15.330914458901074
              ],
              [
                6.309427757995552,
                16.63182739869397
              ],
              [
                10.66748610630176,
                20.100928571475027
              ],
              [
                15.220681395576902,
                23.830212332214668
              ],
              [
                17.497279040214472,
                26.605493270439517
              ],
              [
                18.53800939204879,
                27.906406210232415
              ],
              [
                19.969013625820974,
                30.421504560498686
              ],
              [
                21.33497221260352,
                32.936602910764954
              ],
              [
                23.026159034334285,
                37.96679961129749
              ],
              [
                23.546524210251444,
                38.226982199256064
              ],
              [
                25.62798491392008,
                38.40043725789512
              ],
              [
                27.9696282055473,
                38.40043725789512
              ],
              [
                30.831636673091673,
                38.226982199256064
              ],
              [
                33.17327996471889,
                38.57389231653417
              ],
              [
                33.953827728594625,
                39.26771255109038
              ],
              [
                35.5149232563461,
                40.82880807884187
              ],
              [
                36.29547102022184,
                42.12972101863476
              ],
              [
                36.815836196139,
                43.257178899788606
              ],
              [
                37.46629266603545,
                43.08372384114955
              ],
              [
                38.18179478292155,
                43.08372384114955
              ],
              [
                38.7021599588387,
                43.69081654638624
              ],
              [
                39.67784466368337,
                43.69081654638624
              ],
              [
                41.04380325046592,
                43.51736148774719
              ],
              [
                42.21462489627953,
                45.94573230869393
              ],
              [
                42.80003571918633,
                47.59355536576493
              ],
              [
                43.58058348306207,
                48.72101324691877
              ],
              [
                43.97085736499993,
                51.32283912650456
              ],
              [
                43.775720424031,
                52.53702453697794
              ],
              [
                43.97085736499993,
                57.91413135478858
              ],
              [
                43.90581171801029,
                59.90886452913769
              ],
              [
                43.90581171801029,
                61.64341511552822
              ],
              [
                42.80003571918633,
                62.51069040872349
              ],
              [
                42.084533602300226,
                62.2505078207649
              ],
              [
                41.75930536735201,
                63.37796570191875
              ],
              [
                41.43407713240378,
                63.81160334851638
              ],
              [
                40.653529368528055,
                64.41869605375307
              ],
              [
                39.54775336970408,
                64.67887864171165
              ],
              [
                39.09243384077657,
                64.8523337003507
              ],
              [
                39.027388193786926,
                66.06651911082406
              ],
              [
                38.37693172389047,
                66.76033934538027
              ],
              [
                37.72647525399403,
                66.8470668746998
              ],
              [
                37.46629266603545,
                64.93906122967023
              ],
              [
                36.88088184312864,
                64.8523337003507
              ],
              [
                37.07601878409758,
                67.02052193333886
              ],
              [
                36.62069925517007,
                68.32143487313176
              ],
              [
                35.38483196236682,
                68.75507251972938
              ],
              [
                34.14896466956356,
                68.58161746109033
              ],
              [
                34.21401031655321,
                66.67361181606076
              ],
              [
                30.376317144164155,
                66.67361181606076
              ],
              [
                29.205495498350547,
                66.76033934538027
              ],
              [
                28.81522161641268,
                69.79580287156372
              ],
              [
                28.685130322433388,
                74.13217933754004
              ],
              [
                28.620084675443742,
                76.47382262916726
              ],
              [
                26.538623971775106,
                77.08091533440393
              ],
              [
                24.0668893861686,
                76.82073274644536
              ],
              [
                23.741661151220374,
                75.43309227733292
              ],
              [
                23.481478563261803,
                74.13217933754004
              ],
              [
                22.245611270458546,
                75.17290968937435
              ],
              [
                21.07478962464494,
                76.38709509984771
              ],
              [
                20.489378801738134,
                78.12164568623825
              ],
              [
                19.969013625820974,
                82.71820474017316
              ],
              [
                19.708831037862396,
                84.62621038520273
              ],
              [
                17.75746162817305,
                86.81741554343193
              ],
              [
                15.741046571494058,
                86.90414307275148
              ],
              [
                13.72463151481507,
                86.38377789683432
              ],
              [
                12.29362728104288,
                86.38377789683432
              ],
              [
                10.667486106301757,
                83.00140425337278
              ],
              [
                10.147120930384599,
                81.70049131357989
              ],
              [
                9.236481872529572,
                81.35358119630179
              ],
              [
                7.285112462840225,
                80.22612331514794
              ],
              [
                4.94346917121301,
                79.53230308059173
              ],
              [
                1.6261411747411216,
                80.13939578582843
              ],
              [
                0,
                80.13939578582843
              ]
            ],
            "closed": true,
            "polygonlabels": [
              "car"
            ]
          },
          "id": "vk8tvUlgu4",
          "from_name": "label",
          "to_name": "image",
          "type": "polygonlabels",
          "origin": "manual"
        },
        {
          "original_width": 640,
          "original_height": 480,
          "image_rotation": 0,
          "value": {
            "points": [
              [
                47.54297374787203,
                58.275187623177416
              ],
              [
                47.55458776850654,
                56.900125356661604
              ],
              [
                47.571716320315474,
                56.32917362969715
              ],
              [
                47.67448763116907,
                56.16930714614709
              ],
              [
                48.068444322774546,
                56.16930714614709
              ],
              [
                48.20547273724601,
                55.00456562313962
              ],
              [
                48.42814391076215,
                54.50212810341089
              ],
              [
                49.0105146722659,
                54.22807127446795
              ],
              [
                51.52841178817915,
                54.25090934354653
              ],
              [
                52.607510552141974,
                53.999690583682174
              ],
              [
                53.24126696907252,
                54.410775827096586
              ],
              [
                53.600966557060126,
                55.00456562313962
              ],
              [
                53.84076628238518,
                55.940926455361314
              ],
              [
                53.89215193781199,
                56.4890401132472
              ],
              [
                54.097694559519205,
                56.7859350112687
              ],
              [
                54.25185152579961,
                57.4254009454689
              ],
              [
                54.457394147506804,
                57.60810549809752
              ],
              [
                54.85135083911228,
                57.790810050726144
              ],
              [
                54.68006532102295,
                58.63581860663354
              ],
              [
                54.474522699315735,
                59.06974191912652
              ],
              [
                54.44026559569787,
                60.18880730397686
              ],
              [
                54.59442256197827,
                61.74179600132019
              ],
              [
                53.89215193781199,
                61.764634070398756
              ],
              [
                53.27552407269038,
                61.69611986316303
              ],
              [
                53.10423855460105,
                61.05665392896283
              ],
              [
                51.95662558340249,
                61.079491998041405
              ],
              [
                50.363670265171656,
                61.14800620527714
              ],
              [
                49.45585701929817,
                61.14800620527714
              ],
              [
                48.97625756864804,
                60.87394937633421
              ],
              [
                48.9591290168391,
                61.67328179408445
              ],
              [
                48.39388680714429,
                61.87882441579165
              ],
              [
                47.99993011553882,
                61.81031020855591
              ]
            ],
            "closed": true,
            "polygonlabels": [
              "car"
            ]
          },
          "id": "aoLlp8kJBy",
          "from_name": "label",
          "to_name": "image",
          "type": "polygonlabels",
          "origin": "manual"
        },
        {
          "original_width": 640,
          "original_height": 480,
          "image_rotation": 0,
          "value": {
            "points": [
              [
                55.06647431830062,
                55.35977483818678
              ],
              [
                55.032217214682746,
                56.82141125921579
              ],
              [
                54.68964617850407,
                57.07263001908015
              ],
              [
                54.706774730313015,
                57.68925788420176
              ],
              [
                55.68310218342223,
                57.62074367696602
              ],
              [
                55.6659736316133,
                55.451127114501105
              ],
              [
                55.18637418096315,
                55.131394147401004
              ]
            ],
            "closed": true,
            "polygonlabels": [
              "color_cone"
            ]
          },
          "id": "MK0dX37QTM",
          "from_name": "label",
          "to_name": "image",
          "type": "polygonlabels",
          "origin": "manual"
        },
        {
          "original_width": 640,
          "original_height": 480,
          "image_rotation": 0,
          "value": {
            "points": [
              [
                63.9633471266186,
                58.94548774780751
              ],
              [
                63.9633471266186,
                55.476386575026446
              ],
              [
                63.24784500973251,
                55.302931516387396
              ],
              [
                62.987662421773926,
                54.435656223192126
              ],
              [
                63.70316453866002,
                54.52238375251166
              ],
              [
                63.573073244680735,
                54.0020185765945
              ],
              [
                63.24784500973251,
                52.87456069544065
              ],
              [
                63.83325583263932,
                52.614378107482075
              ],
              [
                64.15848406758754,
                53.74183598863592
              ],
              [
                64.54875794952541,
                53.56838092999687
              ],
              [
                64.93903183146327,
                56.777299514819354
              ],
              [
                64.80894053748399,
                59.5525804530442
              ],
              [
                64.87398618447364,
                60.94022092215663
              ]
            ],
            "closed": true,
            "polygonlabels": [
              "person"
            ]
          },
          "id": "IdMjNik_Cc",
          "from_name": "label",
          "to_name": "image",
          "type": "polygonlabels",
          "origin": "manual"
        },
        {
          "original_width": 640,
          "original_height": 480,
          "image_rotation": 0,
          "value": {
            "points": [
              [
                71.69006375094261,
                59.79704235439234
              ],
              [
                71.26373923498379,
                59.89735400520618
              ],
              [
                71.16342758416995,
                58.09174429055708
              ],
              [
                71.89068705257029,
                55.416766935521366
              ],
              [
                70.96280428254227,
                55.483641369397255
              ],
              [
                71.03803802065266,
                54.94864589839011
              ],
              [
                71.56467418742531,
                54.814897030638335
              ],
              [
                71.81545331445992,
                54.51396207819682
              ],
              [
                72.41732321934295,
                54.54739929513476
              ],
              [
                72.99411521152253,
                54.34677599350708
              ],
              [
                73.21981642585365,
                55.5839530202111
              ],
              [
                72.51763487015678,
                55.5839530202111
              ],
              [
                72.24177783041871,
                56.453320660597704
              ],
              [
                72.16654409230834,
                57.22237665017047
              ],
              [
                71.89068705257029,
                58.024869856681185
              ]
            ],
            "closed": true,
            "polygonlabels": [
              "car_stop"
            ]
          },
          "id": "1cGl2q4kFR",
          "from_name": "label",
          "to_name": "image",
          "type": "polygonlabels",
          "origin": "manual"
        },
        {
          "original_width": 640,
          "original_height": 480,
          "image_rotation": 0,
          "value": {
            "points": [
              [
                75.67292802587279,
                46.49616418594997
              ],
              [
                75.02247155597635,
                46.75634677390855
              ],
              [
                74.24192379210062,
                50.48563053464819
              ],
              [
                73.78660426317309,
                52.8272738262754
              ],
              [
                73.72155861618346,
                49.01126253621624
              ],
              [
                73.071102146287,
                49.27144512417482
              ],
              [
                72.81091955832842,
                51.35290582784345
              ],
              [
                73.46137602822488,
                51.699815945121564
              ],
              [
                73.59146732220417,
                54.64855194198547
              ],
              [
                73.65651296919381,
                59.24511099592037
              ],
              [
                73.85164991016275,
                63.32130487393811
              ],
              [
                74.37201508607991,
                64.18858016713338
              ],
              [
                75.60788237888316,
                64.18858016713338
              ],
              [
                75.6729280258728,
                62.193846992784266
              ],
              [
                76.64861273071747,
                62.193846992784266
              ],
              [
                76.71365837770713,
                64.70894534305053
              ],
              [
                77.42916049459322,
                65.05585546032864
              ],
              [
                78.4048451994379,
                64.96912793100911
              ],
              [
                78.79511908137576,
                63.49475993257716
              ],
              [
                79.64071249224114,
                63.75494252053575
              ],
              [
                80.4212602561169,
                63.75494252053575
              ],
              [
                81.13676237300298,
                63.40803240325764
              ],
              [
                81.00667107902369,
                66.27004087080202
              ],
              [
                81.39694496096156,
                67.05058863467775
              ],
              [
                81.91731013687871,
                67.31077122263633
              ],
              [
                83.02308613570267,
                67.65768133991445
              ],
              [
                83.34831437065091,
                66.09658581216296
              ],
              [
                84.51913601646451,
                66.27004087080202
              ],
              [
                85.49482072130918,
                66.44349592944107
              ],
              [
                85.68995766227812,
                68.35150157447065
              ],
              [
                86.080231544216,
                69.13204933834639
              ],
              [
                87.12096189605032,
                69.04532180902686
              ],
              [
                89.20242259971896,
                69.39223192630497
              ],
              [
                90.63342683349114,
                69.73914204358307
              ],
              [
                91.023700715429,
                67.57095381059492
              ],
              [
                90.5683811865015,
                64.96912793100911
              ],
              [
                90.76351812747042,
                63.84167004985527
              ],
              [
                91.28388330338758,
                63.32130487393811
              ],
              [
                92.1945223612426,
                63.49475993257716
              ],
              [
                92.51975059619085,
                65.14258298964816
              ],
              [
                92.64984189017014,
                69.56568698494402
              ],
              [
                92.91002447812869,
                72.1675128645298
              ],
              [
                94.27598306491124,
                72.60115051112744
              ],
              [
                95.056530828787,
                72.86133309908602
              ],
              [
                95.25166776975593,
                70.86659992473693
              ],
              [
                96.55258070954882,
                69.73914204358307
              ],
              [
                97.33312847342455,
                69.73914204358307
              ],
              [
                98.30881317826923,
                69.99932463154165
              ],
              [
                100,
                70.25950721950024
              ],
              [
                99.93495435301034,
                42.68015289589081
              ],
              [
                98.76413270719674,
                42.68015289589081
              ],
              [
                97.39817412041421,
                43.54742818908608
              ],
              [
                96.48753506255916,
                44.327975952961815
              ],
              [
                96.0972611806213,
                45.10852371683755
              ],
              [
                94.92643953480768,
                45.2819787754766
              ],
              [
                93.62552659501479,
                44.58815854092039
              ],
              [
                92.3246136552219,
                44.67488607023992
              ],
              [
                91.99938542027365,
                41.46596748541744
              ],
              [
                91.7392028323151,
                40.33850960426359
              ],
              [
                91.34892895037721,
                40.598692192222174
              ],
              [
                91.34892895037721,
                42.419970307932225
              ],
              [
                91.21883765639794,
                43.89433830636418
              ],
              [
                89.98297036359469,
                44.24124842364228
              ],
              [
                88.48692048283284,
                44.501431011600864
              ],
              [
                86.21032283819528,
                44.154520894322765
              ],
              [
                84.77931860442308,
                44.24124842364228
              ],
              [
                84.38904472248522,
                43.11379054248844
              ],
              [
                84.12886213452664,
                42.59342536657128
              ],
              [
                83.73858825258877,
                43.46070065976655
              ],
              [
                83.73858825258877,
                44.58815854092039
              ],
              [
                81.98235578386836,
                44.76161359955944
              ],
              [
                79.7057581392308,
                44.76161359955944
              ],
              [
                78.1446626114793,
                45.368706304796135
              ]
            ],
            "closed": true,
            "polygonlabels": [
              "car"
            ]
          },
          "id": "xXbJe7DWBj",
          "from_name": "label",
          "to_name": "image",
          "type": "polygonlabels",
          "origin": "manual"
        }
      ],
      "was_cancelled": false,
      "ground_truth": false,
      "created_at": "2025-12-10T01:21:14.234730Z",
      "updated_at": "2025-12-10T01:29:03.656400Z",
      "draft_created_at": "2025-12-09T21:36:05.160220Z",
      "lead_time": 600.943,
      "prediction": {},
      "result_count": 6,
      "unique_id": "6f4d6b4c-4bdb-4dea-a059-ddffecfd95c8",
      "import_id": null,
      "last_action": null,
      "bulk_created": false,
      "task": 11564,
      "project": 23,
      "updated_by": 1,
      "parent_prediction": null,
      "parent_annotation": null,
      "last_created_by": null
    }
  ],
  "drafts": [],
  "predictions": [],
  "data": {
    "image": "/data/local-files/?d=proyecto_oct_2025_sam2/dataset/dataset_2025/estadistica/mfnet/tir_images/task_0004.png"
  },
  "meta": {},
  "created_at": "2025-12-10T01:21:14.177284Z",
  "updated_at": "2025-12-10T01:29:07.235499Z",
  "inner_id": 4,
  "total_annotations": 1,
  "cancelled_annotations": 0,
  "total_predictions": 0,
  "comment_count": 0,
  "unresolved_comment_count": 0,
  "last_comment_updated_at": null,
  "project": 23,
  "updated_by": 1,
  "comment_authors": []
}